geopard/geopard.py
geopard/settings.py
geopard/version.py
geopard-0.2.3.dist-info/LICENSE
geopard-0.2.3.dist-info/METADATA
geopard-0.2.3.dist-info/WHEEL
geopard-0.2.3.dist-info/RECORD
