Metadata-Version: 2.1
Name: geopard
Version: 0.2.3
Summary: Matching of gpx segments with dynamic time warping.
License: MIT
Author: danielvogler
Requires-Python: >=3.8,<4.0
Classifier: License :: OSI Approved :: MIT License
Classifier: Programming Language :: Python :: 3
Classifier: Programming Language :: Python :: 3.8
Classifier: Programming Language :: Python :: 3.9
Classifier: Programming Language :: Python :: 3.10
Classifier: Programming Language :: Python :: 3.11
Classifier: Programming Language :: Python :: 3.12
Requires-Dist: Shapely (>=1.7.1,<2.0.0)
Requires-Dist: gpxpy (>=1.5.0,<2.0.0)
Requires-Dist: matplotlib (>=3.6.3,<4.0.0)
Requires-Dist: numpy (>=1.11,<2.0)
Requires-Dist: pylint (>=3.0.2,<4.0.0)
Requires-Dist: pytest (>=7.4.3,<8.0.0)
Requires-Dist: scipy (>=1.5.4,<2.0.0)
Requires-Dist: yamllint (>=1.32.0,<2.0.0)
